{
    "page_views": {
        "weather": 33,
        "events": 10,
        "day_events": 3,
        "contacts": 1,
        "board": 0
    },
    "navigation_inputs": {
        "touchscreen": 39,
        "home_button": 20,
        "vocal_assistant": 21,
        "rfid_cards": 9
    },
    "imu": {
        "state": "idle",
        "movements": 1
    },
    "video_calls": {
        "call_requests": 3,
        "calls_made": 0,
        "last_duration_sec": 0,
        "total_duration_sec": 0
    },
    "board": {
        "received_photos": 1
    },
    "events": {
        "added_events": 0
    },
    "screen_wakeup": {
        "wakeups": 43
    },
    "proximity": {
        "north": {
            "motion_detected": 253,
            "approach_detected": 43
        },
        "south": {
            "motion_detected": 238,
            "approach_detected": 33
        },
        "east": {
            "motion_detected": 204,
            "approach_detected": 9
        },
        "west": {
            "motion_detected": 282,
            "approach_detected": 65
        }
    }
}